nlp_service/__init__.py
nlp_service/__main__.py
nlp_service/client.py
nlp_service/py.typed
nlp_service/server.py
nlp_service-2.0.4.dist-info/licenses/LICENSE
nlp_service-2.0.4.dist-info/METADATA
nlp_service-2.0.4.dist-info/WHEEL
nlp_service-2.0.4.dist-info/entry_points.txt
nlp_service-2.0.4.dist-info/top_level.txt
nlp_service-2.0.4.dist-info/RECORD
