Metadata-Version: 2.4
Name: nlp-service
Version: 2.0.4
Summary: Microservice for NLP tasks using gRPC
Author-email: Mirko Lenz <mirko@mirkolenz.com>
Project-URL: Repository, https://github.com/recap-utr/nlp-service
Project-URL: Documentation, https://recap-utr.github.io/nlp-service/
Project-URL: Issues, https://github.com/recap-utr/nlp-service/issues
Project-URL: Changelog, https://github.com/recap-utr/nlp-service/releases
Classifier: Development Status :: 4 - Beta
Classifier: Intended Audience :: Developers
Classifier: Intended Audience :: Science/Research
Classifier: License :: OSI Approved :: MIT License
Classifier: Natural Language :: English
Classifier: Operating System :: OS Independent
Classifier: Programming Language :: Python :: 3.12
Classifier: Programming Language :: Python :: 3.13
Classifier: Programming Language :: Python :: 3
Classifier: Topic :: Scientific/Engineering :: Artificial Intelligence
Classifier: Topic :: Scientific/Engineering :: Information Analysis
Classifier: Topic :: Software Development :: Libraries :: Python Modules
Classifier: Typing :: Typed
Requires-Python: >=3.12
License-File: LICENSE
Requires-Dist: arg-services<2,>=1.7.7
Requires-Dist: cbrkit[nlp]<1,>=0.28.5
Requires-Dist: numba<1,>=0.61
Requires-Dist: typer<1,>=0.9
Provides-Extra: all
Requires-Dist: cbrkit[llm,transformers]; extra == "all"
Requires-Dist: tensorflow-hub<1,>=0.16; (platform_machine != "x86_64" or sys_platform != "darwin") and extra == "all"
Requires-Dist: tensorflow<3,>=2; (platform_machine != "x86_64" or sys_platform != "darwin") and extra == "all"
Dynamic: license-file
